ansys_corba/CORBA.py
ansys_corba/CosNaming_idl.py
ansys_corba/ICoMapdlUnit_idl.py
ansys_corba/PortableServer.py
ansys_corba/PortableServer__POA.py
ansys_corba/__init__.py
ansys_corba/__init__.py~
ansys_corba/_omnipy.cpython-36m-x86_64-linux-gnu.so
ansys_corba/_omnipy.cpython-36m-x86_64-linux-gnu.so.4
ansys_corba/_omnipy.cpython-36m-x86_64-linux-gnu.so.4.2
ansys_corba/libomniORB4.so.2
ansys_corba/libomnithread.so.4
ansys_corba/omniORB.pth
ansys_corba/AAS_CORBA/__init__.py
ansys_corba/AAS_CORBA/MAPDL/__init__.py
ansys_corba/AAS_CORBA/MAPDL/Exceptions/__init__.py
ansys_corba/AAS_CORBA/MAPDL/Solvers/__init__.py
ansys_corba/AAS_CORBA/MAPDL/Types/__init__.py
ansys_corba/AAS_CORBA__POA/__init__.py
ansys_corba/AAS_CORBA__POA/MAPDL/__init__.py
ansys_corba/AAS_CORBA__POA/MAPDL/Exceptions/__init__.py
ansys_corba/AAS_CORBA__POA/MAPDL/Solvers/__init__.py
ansys_corba/AAS_CORBA__POA/MAPDL/Types/__init__.py
ansys_corba/CosNaming/__init__.py
ansys_corba/CosNaming/__pycache__/__init__.cpython-36.pyc
ansys_corba/CosNaming__POA/__init__.py
ansys_corba/CosNaming__POA/__pycache__/__init__.cpython-36.pyc
ansys_corba/omniORB/BiDirPolicy.py
ansys_corba/omniORB/CORBA.py
ansys_corba/omniORB/Compression.py
ansys_corba/omniORB/PortableServer.py
ansys_corba/omniORB/PortableServer__POA.py
ansys_corba/omniORB/URI.py
ansys_corba/omniORB/ZIOP.py
ansys_corba/omniORB/__init__.py
ansys_corba/omniORB/ami.py
ansys_corba/omniORB/any.py
ansys_corba/omniORB/base.tar
ansys_corba/omniORB/boxes_idl.py
ansys_corba/omniORB/codesets.py
ansys_corba/omniORB/compression_idl.py
ansys_corba/omniORB/corbaidl_idl.py
ansys_corba/omniORB/interceptors.py
ansys_corba/omniORB/ir_idl.py
ansys_corba/omniORB/messaging_idl.py
ansys_corba/omniORB/minorCodes.py
ansys_corba/omniORB/omniConnectionMgmt.py
ansys_corba/omniORB/omniPolicy.py
ansys_corba/omniORB/omniZIOP.py
ansys_corba/omniORB/pollable_idl.py
ansys_corba/omniORB/tcInternal.py
ansys_corba/omniORB/ziop_idl.py
ansys_corba-0.1.0.dist-info/METADATA
ansys_corba-0.1.0.dist-info/RECORD
ansys_corba-0.1.0.dist-info/WHEEL
ansys_corba-0.1.0.dist-info/top_level.txt
