Metadata-Version: 2.1
Name: ansys-corba
Version: 0.1.0
Summary: ANSYS interface using partial files from omniORB and omniORBpy
Home-page: UNKNOWN
Author: Alex Kaszynski
Author-email: akascap@gmail.com
License: UNKNOWN
Keywords: ANSYS CORBA
Platform: UNKNOWN
Classifier: Programming Language :: Python :: 2.7
Classifier: Programming Language :: Python :: 3.5
Classifier: Programming Language :: Python :: 3.6
